{
    "6": [
        [
            0.12416481971740723,
            5376000,
            5275648,
            896
        ],
        [
            0.15164613723754883,
            5376000,
            5275648,
            896
        ],
        [
            0.15909075736999512,
            5376000,
            5275648,
            896
        ],
        [
            0.15265607833862305,
            5376000,
            5275648,
            896
        ],
        [
            0.14640140533447266,
            5376000,
            5275648,
            896
        ],
        [
            0.1414189338684082,
            5376000,
            5275648,
            896
        ],
        [
            0.15141868591308594,
            5376000,
            5275648,
            896
        ],
        [
            0.13590359687805176,
            5376000,
            5275648,
            896
        ],
        [
            0.13788533210754395,
            5364000,
            5263872,
            894
        ],
        [
            0.13588595390319824,
            5376000,
            5275648,
            896
        ]
    ],
    "9": [
        [
            0.2017498016357422,
            7800000,
            7654400,
            1300
        ],
        [
            0.19468474388122559,
            7788000,
            7642624,
            1298
        ],
        [
            0.2096848487854004,
            7776000,
            7630848,
            1296
        ],
        [
            0.1985001564025879,
            7800000,
            7654400,
            1300
        ],
        [
            0.21912050247192383,
            7800000,
            7654400,
            1300
        ],
        [
            0.1921393871307373,
            7788000,
            7642624,
            1298
        ],
        [
            0.18314075469970703,
            7800000,
            7654400,
            1300
        ],
        [
            0.2031395435333252,
            7800000,
            7654400,
            1300
        ],
        [
            0.21513986587524414,
            7776000,
            7630848,
            1296
        ],
        [
            0.1979074478149414,
            7776000,
            7630848,
            1296
        ]
    ],
    "12": [
        [
            0.25792503356933594,
            10056000,
            9868288,
            1676
        ],
        [
            0.2609264850616455,
            10044000,
            9856512,
            1674
        ],
        [
            0.26364707946777344,
            10044000,
            9856512,
            1674
        ],
        [
            0.26302671432495117,
            10056000,
            9868288,
            1676
        ],
        [
            0.25902581214904785,
            10044000,
            9856512,
            1674
        ],
        [
            0.2620260715484619,
            10056000,
            9868288,
            1676
        ],
        [
            0.2600250244140625,
            10020000,
            9832960,
            1670
        ],
        [
            0.23902654647827148,
            10032000,
            9844736,
            1672
        ],
        [
            0.26885437965393066,
            10044000,
            9856512,
            1674
        ],
        [
            0.2540872097015381,
            10044000,
            9856512,
            1674
        ]
    ],
    "18": [
        [
            0.3744473457336426,
            14184000,
            13919232,
            2364
        ],
        [
            0.36844778060913086,
            14148000,
            13883904,
            2358
        ],
        [
            0.439100980758667,
            14196000,
            13931008,
            2366
        ],
        [
            0.37383460998535156,
            14148000,
            13883904,
            2358
        ],
        [
            0.42207860946655273,
            14136000,
            13872128,
            2356
        ],
        [
            0.38802146911621094,
            14184000,
            13919232,
            2364
        ],
        [
            0.40207862854003906,
            14196000,
            13931008,
            2366
        ],
        [
            0.4207570552825928,
            14184000,
            13919232,
            2364
        ],
        [
            0.35053443908691406,
            14148000,
            13883904,
            2358
        ],
        [
            0.3777735233306885,
            14172000,
            13907456,
            2362
        ]
    ],
    "24": [
        [
            0.5322208404541016,
            17628000,
            17298944,
            2938
        ],
        [
            0.4532194137573242,
            17700000,
            17369600,
            2950
        ],
        [
            0.4937570095062256,
            17712000,
            17381376,
            2952
        ],
        [
            0.4636967182159424,
            17652000,
            17322496,
            2942
        ],
        [
            0.5499575138092041,
            17736000,
            17404928,
            2956
        ],
        [
            0.4729011058807373,
            17700000,
            17369600,
            2950
        ],
        [
            0.4963068962097168,
            17748000,
            17416704,
            2958
        ],
        [
            0.5129735469818115,
            17628000,
            17298944,
            2938
        ],
        [
            0.5487215518951416,
            17640000,
            17310720,
            2940
        ],
        [
            0.4687342643737793,
            17676000,
            17346048,
            2946
        ]
    ],
    "36": [
        [
            0.7260720729827881,
            23832000,
            23387136,
            3972
        ],
        [
            0.6466257572174072,
            23892000,
            23446016,
            3982
        ],
        [
            0.6516256332397461,
            23892000,
            23446016,
            3982
        ],
        [
            0.7148697376251221,
            23856000,
            23410688,
            3976
        ],
        [
            0.653860330581665,
            23844000,
            23398912,
            3974
        ],
        [
            0.6831533908843994,
            23832000,
            23387136,
            3972
        ],
        [
            0.6228020191192627,
            23952000,
            23504896,
            3992
        ],
        [
            0.646092414855957,
            23844000,
            23398912,
            3974
        ],
        [
            0.6488137245178223,
            23808000,
            23363584,
            3968
        ],
        [
            0.6860136985778809,
            23772000,
            23328256,
            3962
        ]
    ],
    "48": [
        [
            0.8059210777282715,
            28632000,
            28097536,
            4772
        ],
        [
            0.7232670783996582,
            28740000,
            28203520,
            4790
        ],
        [
            0.822028636932373,
            28632000,
            28097536,
            4772
        ],
        [
            0.8122146129608154,
            28740000,
            28203520,
            4790
        ],
        [
            0.7702138423919678,
            28524000,
            27991552,
            4754
        ],
        [
            0.7730722427368164,
            28704000,
            28168192,
            4784
        ],
        [
            0.8491935729980469,
            28668000,
            28132864,
            4778
        ],
        [
            0.7881772518157959,
            28656000,
            28121088,
            4776
        ],
        [
            0.8101818561553955,
            28632000,
            28097536,
            4772
        ],
        [
            0.7761809825897217,
            28524000,
            27991552,
            4754
        ]
    ],
    "54": [
        [
            0.8439791202545166,
            31080000,
            30499840,
            5180
        ],
        [
            0.8385882377624512,
            30960000,
            30382080,
            5160
        ],
        [
            0.8255884647369385,
            31068000,
            30488064,
            5178
        ],
        [
            0.8023989200592041,
            31080000,
            30499840,
            5180
        ],
        [
            0.7871437072753906,
            31104000,
            30523392,
            5184
        ],
        [
            0.7221479415893555,
            31164000,
            30582272,
            5194
        ],
        [
            0.7236592769622803,
            31116000,
            30535168,
            5186
        ],
        [
            0.6354310512542725,
            30948000,
            30370304,
            5158
        ],
        [
            0.6545178890228271,
            31020000,
            30440960,
            5170
        ],
        [
            0.5941307544708252,
            30852000,
            30276096,
            5142
        ]
    ]
}